relativedeltafield/__init__.py
relativedeltafield/fields.py
relativedeltafield/forms.py
relativedeltafield/utils.py
cval_django_relativedelta-1.1.2.dist-info/LICENSE
cval_django_relativedelta-1.1.2.dist-info/METADATA
cval_django_relativedelta-1.1.2.dist-info/WHEEL
cval_django_relativedelta-1.1.2.dist-info/top_level.txt
cval_django_relativedelta-1.1.2.dist-info/RECORD
